cs.aws_account-1.3.4-py3.13-nspkg.pth
cs/aws_account/__init__.py
cs/aws_account/account.py
cs/aws_account/caching_key.py
cs/aws_account/configure.yaml
cs/aws_account/configure.zcml
cs/aws_account/exceptions.py
cs/aws_account/ftesting.zcml
cs/aws_account/interfaces.py
cs/aws_account/monkies.py
cs/aws_account/regional_account.py
cs/aws_account/regional_account_set.py
cs/aws_account/regional_accounts.py
cs/aws_account/retry.py
cs/aws_account/session.py
cs/aws_account/testing.py
cs/aws_account/b3/__init__.py
cs/aws_account/b3/interfaces.py
cs/aws_account/tests/__init__.py
cs/aws_account/tests/test_account.py
cs/aws_account/tests/test_regional_account.py
cs/aws_account/tests/test_regional_account_set.py
cs/aws_account/tests/test_regional_accounts.py
cs/aws_account/tests/test_session.py
cs_aws_account-1.3.4.data/scripts/lint.sh
cs_aws_account-1.3.4.data/scripts/run-tests.sh
cs_aws_account-1.3.4.dist-info/licenses/LICENSE
cs_aws_account-1.3.4.dist-info/METADATA
cs_aws_account-1.3.4.dist-info/WHEEL
cs_aws_account-1.3.4.dist-info/namespace_packages.txt
cs_aws_account-1.3.4.dist-info/top_level.txt
cs_aws_account-1.3.4.dist-info/RECORD
