Metadata-Version: 2.4
Name: cs.aws_account
Version: 1.3.4
Summary: AWS account components
Home-page: https://github.com/CrowdStrike/cs.aws_account
Author: David Davis
Author-email: david.davis@crowdstrike.com
Maintainer: Forrest Aldridge
Maintainer-email: forrest.aldridge@crowdstrike.com
Classifier: Development Status :: 5 - Production/Stable
Classifier: Intended Audience :: Developers
Classifier: Natural Language :: English
Classifier: Operating System :: Unix
Classifier: Operating System :: POSIX
Classifier: Operating System :: POSIX :: Linux
Classifier: Operating System :: MacOS
Classifier: Operating System :: Microsoft :: Windows
Classifier: Operating System :: OS Independent
Classifier: Programming Language :: Python
Classifier: Programming Language :: Python :: 3
Classifier: Programming Language :: Python :: 3.8
Classifier: Programming Language :: Python :: 3.9
Classifier: Programming Language :: Python :: 3.10
Classifier: Programming Language :: Python :: 3.11
Classifier: Programming Language :: Python :: 3.12
Classifier: Framework :: Zope
Classifier: Framework :: Flake8
Classifier: License :: OSI Approved :: MIT License
Classifier: Topic :: Software Development :: Libraries :: Python Modules
Classifier: Topic :: Utilities
Requires-Python: >=3.8
License-File: LICENSE
Requires-Dist: setuptools
Requires-Dist: zope.security
Requires-Dist: zope.component
Requires-Dist: zope.interface
Requires-Dist: zope.schema
Requires-Dist: boto3
Requires-Dist: botocore
Requires-Dist: cachetools
Requires-Dist: cs.ratelimit
Provides-Extra: dev
Requires-Dist: zope.testrunner; extra == "dev"
Requires-Dist: zope.configuration; extra == "dev"
Requires-Dist: bandit; extra == "dev"
Requires-Dist: coverage; extra == "dev"
Requires-Dist: pyyaml; extra == "dev"
Requires-Dist: Jinja2; extra == "dev"
Requires-Dist: flake8; extra == "dev"
Requires-Dist: pydocstyle; extra == "dev"
Requires-Dist: pylint; extra == "dev"
Dynamic: author
Dynamic: author-email
Dynamic: classifier
Dynamic: description
Dynamic: description-content-type
Dynamic: home-page
Dynamic: license-file
Dynamic: maintainer
Dynamic: maintainer-email
Dynamic: provides-extra
Dynamic: requires-dist
Dynamic: requires-python
Dynamic: summary
